dict2pdf/__init__.py
dict2pdf/generator.py
dict2pdf/styles.py
tests/__init__.py
tests/test_base.py
tests/test_create_paragraph.py
tests/test_create_table.py
tests/test_format_value.py
tests/test_generate_pdf.py
tests/test_generate_table.py
tests/test_merge_styles.py
dict2pdf-1.0.0.dist-info/METADATA
dict2pdf-1.0.0.dist-info/WHEEL
dict2pdf-1.0.0.dist-info/top_level.txt
dict2pdf-1.0.0.dist-info/RECORD
