Metadata-Version: 2.4
Name: dict2pdf
Version: 1.0.0
Summary: A package for generating PDFs from structured data
Home-page: https://github.com/dannyyol/dict2pdf
Project-URL: Homepage, https://github.com/dannyyol/dict2pdf
Project-URL: Bug Tracker, https://github.com/dannyyol/dict2pdf/issues
Classifier: Programming Language :: Python :: 3.13
Classifier: License :: OSI Approved :: MIT License
Classifier: Operating System :: OS Independent
Requires-Python: >=3.6
Requires-Dist: reportlab>=3.6.12
Requires-Dist: pandas>=1.3.0
Dynamic: classifier
Dynamic: description
Dynamic: description-content-type
Dynamic: home-page
Dynamic: project-url
Dynamic: requires-dist
Dynamic: requires-python
Dynamic: summary
